{"id":"1mkrfedhrewayxy0j3hs899","title":"AAA","desc":"","updated":1653097621095,"created":1653097334047,"custom":{},"fname":"CIA-triad.AAA","type":"note","vault":{"fsPath":"vault"},"contentHash":"fb0098f39349592be88039def2790337","links":[],"anchors":{"authentication-and-access-control":{"type":"header","text":"Authentication and Access Control","value":"authentication-and-access-control","line":8,"column":0,"depth":1},"authentication-and-aaa":{"type":"header","text":"Authentication and AAA","value":"authentication-and-aaa","line":22,"column":0,"depth":2},"authentication-methods":{"type":"header","text":"Authentication Methods","value":"authentication-methods","line":32,"column":0,"depth":2},"controls":{"type":"header","text":"Controls","value":"controls","line":39,"column":0,"depth":2},"types":{"type":"header","text":"Types","value":"types","line":41,"column":0,"depth":3},"each-control-type":{"type":"header","text":"Each Control Type","value":"each-control-type","line":52,"column":0,"depth":4},"access-control-methods":{"type":"header","text":"Access Control Methods","value":"access-control-methods","line":68,"column":0,"depth":2},"mac---mandatory-access-control":{"type":"header","text":"MAC - Mandatory Access Control","value":"mac---mandatory-access-control","line":72,"column":0,"depth":3},"dac---discretionary-access-control":{"type":"header","text":"DAC - Discretionary Access Control","value":"dac---discretionary-access-control","line":78,"column":0,"depth":3},"role-based-access-control":{"type":"header","text":"Role Based Access Control","value":"role-based-access-control","line":82,"column":0,"depth":3},"centralized":{"type":"header","text":"Centralized","value":"centralized","line":88,"column":0,"depth":3},"decentralized":{"type":"header","text":"Decentralized","value":"decentralized","line":94,"column":0,"depth":3},"best-practices-for-access-control-field":{"type":"header","text":"Best Practices for Access Control Field","value":"best-practices-for-access-control-field","line":101,"column":0,"depth":2},"least-privilege":{"type":"header","text":"Least Privilege","value":"least-privilege","line":105,"column":0,"depth":3},"separation-of-duties":{"type":"header","text":"Separation of Duties","value":"separation-of-duties","line":109,"column":0,"depth":3},"rotation-of-duties":{"type":"header","text":"Rotation of Duties","value":"rotation-of-duties","line":113,"column":0,"depth":3},"physical-and-logical":{"type":"header","text":"Physical and Logical","value":"physical-and-logical","line":119,"column":0,"depth":2},"physical-methods":{"type":"header","text":"Physical Methods","value":"physical-methods","line":121,"column":0,"depth":3},"technical-use-physical-security-controls":{"type":"header","text":"Technical use Physical Security Controls","value":"technical-use-physical-security-controls","line":128,"column":0,"depth":4},"logical-methods":{"type":"header","text":"Logical Methods","value":"logical-methods","line":139,"column":0,"depth":3},"monitoring-access-control":{"type":"header","text":"Monitoring Access Control","value":"monitoring-access-control","line":157,"column":0,"depth":4}},"children":[],"parent":"cl0utj7thwjp7bsmxe4v5va","data":{}}
