{"id":"mqe5q0prgv6j0ihv940jvuu","title":"Compliance","desc":"","updated":1653130950551,"created":1653130601501,"custom":{},"fname":"industry-standards.compliance","type":"note","vault":{"fsPath":"vault"},"contentHash":"d712c308f674d574f0769cb80b15c7cf","links":[],"anchors":{"compliance-and-regulation-for-cybersecurity":{"type":"header","text":"Compliance and Regulation for Cybersecurity","value":"compliance-and-regulation-for-cybersecurity","line":8,"column":0,"depth":1},"definitions":{"type":"header","text":"Definitions","value":"definitions","line":26,"column":0,"depth":2},"challenges":{"type":"header","text":"Challenges","value":"challenges","line":37,"column":0,"depth":3},"compliance-basics---security-privacy-and-compliance":{"type":"header","text":"Compliance Basics - Security, Privacy and Compliance","value":"compliance-basics---security-privacy-and-compliance","line":49,"column":0,"depth":2},"security":{"type":"header","text":"Security","value":"security","line":53,"column":0,"depth":3},"privacy":{"type":"header","text":"Privacy","value":"privacy","line":63,"column":0,"depth":3},"compliance":{"type":"header","text":"Compliance","value":"compliance","line":67,"column":0,"depth":3},"foundational":{"type":"header","text":"Foundational","value":"foundational","line":73,"column":0,"depth":4},"industry":{"type":"header","text":"Industry","value":"industry","line":77,"column":0,"depth":4},"compliance-process":{"type":"header","text":"Compliance Process","value":"compliance-process","line":81,"column":0,"depth":4},"overview-us-cybersecurity-federal-law":{"type":"header","text":"Overview US Cybersecurity Federal Law","value":"overview-us-cybersecurity-federal-law","line":97,"column":0,"depth":2},"us-federal-laws":{"type":"header","text":"US Federal Laws","value":"us-federal-laws","line":102,"column":0,"depth":3},"national-institute-of-standards-and-technology-nist-overview":{"type":"header","text":"National Institute of Standards and Technology (NIST) Overview","value":"national-institute-of-standards-and-technology-nist-overview","line":113,"column":0,"depth":2},"general-data-protection-regulation-gdpr":{"type":"header","text":"General Data Protection Regulation (GDPR)","value":"general-data-protection-regulation-gdpr","line":121,"column":0,"depth":2},"5-key-general-data-protection-regulation-obligations":{"type":"header","text":"5 Key General Data Protection Regulation Obligations","value":"5-key-general-data-protection-regulation-obligations","line":128,"column":0,"depth":3},"key-terms":{"type":"header","text":"Key Terms","value":"key-terms","line":136,"column":0,"depth":3},"international-organization-for-standardization-iso-2700x":{"type":"header","text":"International Organization for Standardization (ISO) 2700x","value":"international-organization-for-standardization-iso-2700x","line":157,"column":0,"depth":2}},"children":[],"parent":"e77elhqi5fhnpz5kdvxeudb","data":{}}
